simple_telegram/__init__.py
simple_telegram/telegram.py
simple_telegram-0.2.dist-info/LICENSE
simple_telegram-0.2.dist-info/METADATA
simple_telegram-0.2.dist-info/WHEEL
simple_telegram-0.2.dist-info/top_level.txt
simple_telegram-0.2.dist-info/RECORD
