Metadata-Version: 2.1
Name: simple_telegram
Version: 0.2
Summary: For sending and receiving messages using Telegram
Home-page: https://github.com/alex-merge/Simple-Telegram
Author: Alexis M.
Classifier: Programming Language :: Python :: 3
Classifier: License :: OSI Approved :: MIT License
Classifier: Operating System :: OS Independent
Requires-Python: >=3.7
License-File: LICENSE
